{
	"sales": [
		{
			"product_id": "0192568",
			"channel_id": 1,
			"count": 2,
			"date": "2017-11-23T09:10:37+01:00"
		},
		{
			"product_id": "0195675",
			"channel_id": 1,
			"count": 1,
			"date": "2017-11-23T09:15:37+01:00"
		},
		{
			"product_id": "0187995",
			"channel_id": 2,
			"count": 1,
			"date": "2017-11-23T09:15:37+01:00"
		},
		{
			"product_id": "0194647",
			"channel_id": 3,
			"count": 2,
			"date": "2017-11-23T09:22:58+01:00"
		},
		{
			"product_id": "0195473",
			"channel_id": 4,
			"count": 1,
			"date": "2017-11-23T09:11:58+01:00"
		},
		{
			"product_id": "0196247",
			"channel_id": 1,
			"count": 4,
			"date": "2017-11-23T00:15:37+01:00"
		}
	],
	"channels": [
		{
			"id": 1,
			"name": "Sprinter"
		},
		{
			"id": 2,
			"name": "App"
		},
		{
			"id": 3,
			"name": "Sprinter.es"
		},
		{
			"id": 4,
			"name": "Marketplaces"
		}
	]
}